chakin/__init__.py
chakin/datasets.csv
chakin/downloader.py
chakin-0.0.8.dist-info/DESCRIPTION.rst
chakin-0.0.8.dist-info/METADATA
chakin-0.0.8.dist-info/RECORD
chakin-0.0.8.dist-info/WHEEL
chakin-0.0.8.dist-info/metadata.json
chakin-0.0.8.dist-info/top_level.txt
