Metadata-Version: 2.0
Name: chakin
Version: 0.0.8
Summary: Downloader for pre-trained word vectors
Home-page: https://github.com/chakki-works/chakin
Author: Hironsan
Author-email: hiroki.nakayama.py@gmail.com
License: MIT
Keywords: machine learning,natural language processing,word embeddings,downloader
Platform: UNKNOWN
Requires-Dist: pandas (>=0.20.1)
Requires-Dist: progressbar2 (>=3.20.0)
Requires-Dist: six (>=1.10.0)
